lpcf/config.py
lpcf/pcf.py
lpcf/utils.py
lpcf-0.1.0.dist-info/licenses/LICENSE
lpcf-0.1.0.dist-info/METADATA
lpcf-0.1.0.dist-info/WHEEL
lpcf-0.1.0.dist-info/top_level.txt
lpcf-0.1.0.dist-info/RECORD
