Metadata-Version: 2.4
Name: lpcf
Version: 0.1.0
Summary: Learning parametric convex functions
Author-email: Maximilian Schaller <mschall@stanford.edu>, Alberto Bemporad <alberto.bemporad@imtlucca.it>
License: Apache 2.0
Project-URL: Homepage, https://github.com/cvxgrp/lpcf
Requires-Python: >=3.10
License-File: LICENSE
Requires-Dist: jax-sysid>=1.0.6
Requires-Dist: cvxpy>=1.6.0
Requires-Dist: numpy>=1.21.6
Dynamic: license-file
